{
  "Subscribers": [
    {
      "id": "b506",
      "email": "vasanth115@gmail.com",
      "password": "vasanth115"
    },
    {
      "id": "972b",
      "email": "vasanthmoorthi4504@gmail.com",
      "password": "vasanth215"
    },
    {
      "id": "d1d6",
      "email": "jayadev@gmail.com",
      "password": "jayadev@1234"
    },
    {
      "id": "a9aa",
      "email": "subash@gmail.com",
      "password": "subash"
    },
    {
      "id": "8d5f",
      "email": "ranjith@gmail.com",
      "password": "ranjith@1234"
    },
    {
      "id": "e1d6",
      "email": "suthrasan@gmail.com",
      "password": "dMpnwEGzHa"
    },
    {
      "id": "efb1",
      "email": "vasanth1151@gmail.com",
      "password": "pfCMccYVKP"
    },
    {
      "id": "1539",
      "email": "pradeepsudhrsan@gmail.com",
      "password": "pradeep@123456789"
    },
    {
      "id": "11be",
      "email": "jeeva@gmail.com",
      "password": "FsduJfPjFS"
    }
  ]
}
